PyCrypCli/__init__.py
PyCrypCli/client.py
PyCrypCli/exceptions.py
PyCrypCli/pycrypcli.py
PyCrypCli/timer.py
PyCrypCli/util.py
PyCrypCli/commands/__init__.py
PyCrypCli/commands/account.py
PyCrypCli/commands/command.py
PyCrypCli/commands/device.py
PyCrypCli/commands/files.py
PyCrypCli/commands/help.py
PyCrypCli/commands/inventory.py
PyCrypCli/commands/miner.py
PyCrypCli/commands/morphcoin.py
PyCrypCli/commands/network.py
PyCrypCli/commands/service.py
PyCrypCli/commands/shell.py
PyCrypCli/commands/shop.py
PyCrypCli/commands/status.py
PyCrypCli/context/__init__.py
PyCrypCli/context/context.py
PyCrypCli/context/device_context.py
PyCrypCli/context/login_context.py
PyCrypCli/context/main_context.py
PyCrypCli/context/root_context.py
PyCrypCli/game_objects/__init__.py
PyCrypCli/game_objects/device.py
PyCrypCli/game_objects/device_hardware.py
PyCrypCli/game_objects/file.py
PyCrypCli/game_objects/game_object.py
PyCrypCli/game_objects/inventory_element.py
PyCrypCli/game_objects/resource_usage.py
PyCrypCli/game_objects/transaction.py
PyCrypCli/game_objects/network/__init__.py
PyCrypCli/game_objects/network/network.py
PyCrypCli/game_objects/network/network_invitation.py
PyCrypCli/game_objects/network/network_membership.py
PyCrypCli/game_objects/service/__init__.py
PyCrypCli/game_objects/service/bruteforce_service.py
PyCrypCli/game_objects/service/miner.py
PyCrypCli/game_objects/service/portscan_service.py
PyCrypCli/game_objects/service/public_service.py
PyCrypCli/game_objects/service/service.py
PyCrypCli/game_objects/shop/__init__.py
PyCrypCli/game_objects/shop/shop_category.py
PyCrypCli/game_objects/shop/shop_product.py
PyCrypCli/game_objects/wallet/__init__.py
PyCrypCli/game_objects/wallet/public_wallet.py
PyCrypCli/game_objects/wallet/wallet.py
PyCrypCli-2.0.1.dist-info/LICENSE
PyCrypCli-2.0.1.dist-info/METADATA
PyCrypCli-2.0.1.dist-info/WHEEL
PyCrypCli-2.0.1.dist-info/entry_points.txt
PyCrypCli-2.0.1.dist-info/top_level.txt
PyCrypCli-2.0.1.dist-info/RECORD
