Metadata-Version: 2.1
Name: PyCrypCli
Version: 2.0.1
Summary: Python Cryptic Game Client
Home-page: https://github.com/Defelo/PyCrypCli
Author: Defelo
Author-email: elodef42@gmail.com
License: UNKNOWN
Platform: UNKNOWN
License-File: LICENSE
Requires-Dist: websocket-client (~=1.3)
Requires-Dist: pyreadline (~=2.1)
Requires-Dist: pypresence (~=4.2)
Requires-Dist: python-dateutil (~=2.8)
Requires-Dist: sentry-sdk (~=1.5)
Requires-Dist: requests (~=2.27)
